{
  "project_info": {
    "project_number": "301424068144",
    "firebase_url": "https://finalproject-1597e.firebaseio.com",
    "project_id": "finalproject-1597e",
    "storage_bucket": "finalproject-1597e.appspot.com"
  },
  "client": [
    {
      "client_info": {
        "mobilesdk_app_id": "1:301424068144:android:750ee59e85beb541",
        "android_client_info": {
          "package_name": "com.example.iteradmin.finalproject"
        }
      },
      "oauth_client": [
        {
          "client_id": "301424068144-64gm656envjq7kh4g804d4hgollonire.apps.googleusercontent.com",
          "client_type": 3
        }
      ],
      "api_key": [
        {
          "current_key": "AIzaSyDDti_2l8IZMjufQCULNkVHN-E2FJTsK6c"
        }
      ],
      "services": {
        "appinvite_service": {
          "other_platform_oauth_client": [
            {
              "client_id": "301424068144-64gm656envjq7kh4g804d4hgollonire.apps.googleusercontent.com",
              "client_type": 3
            }
          ]
        }
      }
    }
  ],
  "configuration_version": "1"
}